upcloud_api/__init__.py
upcloud_api/api.py
upcloud_api/credentials.py
upcloud_api/errors.py
upcloud_api/firewall.py
upcloud_api/host.py
upcloud_api/interface.py
upcloud_api/ip_address.py
upcloud_api/ip_network.py
upcloud_api/label.py
upcloud_api/load_balancer.py
upcloud_api/network.py
upcloud_api/object_storage.py
upcloud_api/router.py
upcloud_api/server.py
upcloud_api/server_group.py
upcloud_api/storage.py
upcloud_api/storage_import.py
upcloud_api/tag.py
upcloud_api/upcloud_resource.py
upcloud_api/utils.py
upcloud_api/cloud_manager/__init__.py
upcloud_api/cloud_manager/firewall_mixin.py
upcloud_api/cloud_manager/host_mixin.py
upcloud_api/cloud_manager/ip_address_mixin.py
upcloud_api/cloud_manager/lb_mixin.py
upcloud_api/cloud_manager/network_mixin.py
upcloud_api/cloud_manager/object_storage_mixin.py
upcloud_api/cloud_manager/server_mixin.py
upcloud_api/cloud_manager/storage_mixin.py
upcloud_api/cloud_manager/tag_mixin.py
upcloud_api-2.8.0.dist-info/METADATA
upcloud_api-2.8.0.dist-info/WHEEL
upcloud_api-2.8.0.dist-info/top_level.txt
upcloud_api-2.8.0.dist-info/RECORD
