Metadata-Version: 2.4
Name: upcloud_api
Version: 2.8.0
Summary: UpCloud API Client
Home-page: https://github.com/UpCloudLtd/upcloud-python-api
Maintainer: UpCloud
Maintainer-email: hello@upcloud.com
License: MIT
Requires-Python: <4,>=3.9
Requires-Dist: requests
Provides-Extra: keyring
Requires-Dist: keyring>=23.0; extra == "keyring"
